ucsd_ece_courses/__init__.py
ucsd_ece_courses/ece_catalog.py
ucsd_ece_courses-0.0.1.dist-info/LICENSE
ucsd_ece_courses-0.0.1.dist-info/METADATA
ucsd_ece_courses-0.0.1.dist-info/WHEEL
ucsd_ece_courses-0.0.1.dist-info/top_level.txt
ucsd_ece_courses-0.0.1.dist-info/RECORD
