Metadata-Version: 2.1
Name: ucsd-ece-courses
Version: 0.0.1
Summary: UCSD ECE Department's course catalog
Author: kendrick010
Author-email: ken010@ucsd.edu
Keywords: python,ucsd,web-scraping
Classifier: License :: OSI Approved :: MIT License
Classifier: Intended Audience :: Developers
Classifier: Programming Language :: Python :: 3
Requires-Python: >=3.10
License-File: LICENSE
Requires-Dist: requests
Requires-Dist: beautifulsoup4
Provides-Extra: dev
Requires-Dist: wheel ; extra == 'dev'
Requires-Dist: twine ; extra == 'dev'
